sc_analyzer_base/__init__.py
sc_analyzer_base/analyzer/__init__.py
sc_analyzer_base/analyzer/base_analyzer.py
sc_analyzer_base/analyzer/base_summary_diff_analyzer.py
sc_analyzer_base/utils/__init__.py
sc_analyzer_base/utils/branch_utils.py
sc_analyzer_base/utils/manifest_utils.py
sc_analyzer_base/utils/money_utils.py
sc_analyzer_base-0.0.27.dist-info/LICENSE
sc_analyzer_base-0.0.27.dist-info/METADATA
sc_analyzer_base-0.0.27.dist-info/WHEEL
sc_analyzer_base-0.0.27.dist-info/entry_points.txt
sc_analyzer_base-0.0.27.dist-info/top_level.txt
sc_analyzer_base-0.0.27.dist-info/RECORD
