Metadata-Version: 2.1
Name: sc-analyzer-base
Version: 0.0.27
Summary: python project
Author: Scott
License: MIT
Keywords: python
Classifier: Programming Language :: Python :: 3
Classifier: Programming Language :: Python :: 3.8
Classifier: Programming Language :: Python :: 3.9
Classifier: Programming Language :: Python :: 3.10
Classifier: Programming Language :: Python :: 3.11
Classifier: Operating System :: OS Independent
Classifier: Topic :: Software Development
Classifier: Topic :: Utilities
License-File: LICENSE
Requires-Dist: sc-utilities>=0.0.17
Requires-Dist: pandas>=1.5.3
